sphinx_multiversion/__init__.py
sphinx_multiversion/__main__.py
sphinx_multiversion/git.py
sphinx_multiversion/main.py
sphinx_multiversion/sphinx.py
sphinx_multiversion_contrib-0.3.2.dist-info/AUTHORS.rst
sphinx_multiversion_contrib-0.3.2.dist-info/LICENSE.rst
sphinx_multiversion_contrib-0.3.2.dist-info/METADATA
sphinx_multiversion_contrib-0.3.2.dist-info/WHEEL
sphinx_multiversion_contrib-0.3.2.dist-info/entry_points.txt
sphinx_multiversion_contrib-0.3.2.dist-info/top_level.txt
sphinx_multiversion_contrib-0.3.2.dist-info/RECORD
