Metadata-Version: 2.1
Name: sphinx-multiversion-contrib
Version: 0.3.2
Summary: Add support for multiple versions to sphinx
Author-email: IQM Finland Oy <developers@meetiqm.com>
License: BSD 2-Clause License
Project-URL: homepage, https://github.com/iqm-finland/sphinx-multiversion-contrib
Project-URL: documentation, https://iqm-finland.github.io/sphinx-multiversion-contrib
Project-URL: repository, https://github.com/iqm-finland/sphinx-multiversion-contrib.git
Project-URL: changelog, https://github.com/iqm-finland/sphinx-multiversion-contrib/blob/main/CHANGELOG.rst
Classifier: Programming Language :: Python :: 3 :: Only
Classifier: License :: OSI Approved :: BSD License
Requires-Python: <3.12,>=3.9
License-File: LICENSE.rst
License-File: AUTHORS.rst
Requires-Dist: sphinx >=4.5.0
Requires-Dist: packaging >=23.0
Provides-Extra: cicd
Requires-Dist: twine ~=4.0 ; extra == 'cicd'
Provides-Extra: dev
Requires-Dist: tox ==4.3.5 ; extra == 'dev'
Provides-Extra: docs
Requires-Dist: sphinx-book-theme ==0.3.3 ; extra == 'docs'
Provides-Extra: test
Requires-Dist: black ==23.7.0 ; extra == 'test'
Requires-Dist: isort ==5.12.0 ; extra == 'test'
Requires-Dist: mypy ==1.5.0 ; extra == 'test'
Requires-Dist: pylint ==2.17.5 ; extra == 'test'
Requires-Dist: pytest ==7.4.0 ; extra == 'test'
Requires-Dist: pytest-cov ==4.1.0 ; extra == 'test'
